aymaralima/libQt5Test.so
aymaralima/libpng16.so
aymaralima/liblima-lp-entitytracker.so
aymaralima/liblima-xp-qtsgmlentities.so
aymaralima/libidn2.so
aymaralima/liblima-lp-textsegmentation.so
aymaralima/libboost_regex.so
aymaralima/liblima-lp-linguisticprocessing-core.so
aymaralima/liblima-lp-propertycode.so
aymaralima/liblima-lp-regexmatcher.so
aymaralima/liblima-lp-analysisdict.so
aymaralima/libicuuc.so
aymaralima/libharfbuzz.so
aymaralima/liblima-common-factory.so
aymaralima/libgraphite2.so
aymaralima/libicui18n.so
aymaralima/liblima-xp-core.so
aymaralima/liblzma.so
aymaralima/liblima-lp-tensorflowmorphosyntax.so
aymaralima/libgcrypt.so
aymaralima/liblima-lp-conllureader.so
aymaralima/liblima-lp-tensorflowlemmatizer.so
aymaralima/libmount.so
aymaralima/liblima-lp-linguisticdata.so
aymaralima/libicudata.so
aymaralima/liblimabinding.so
aymaralima/liblima-lp-automatoncompiler.so
aymaralima/liblima-lp-linguisticanalysisstructure.so
aymaralima/liblima-lp-analysishandlers.so
aymaralima/liblima-lp-helpers.so
aymaralima/liblima-linguisticprocessing.so
aymaralima/libpcre2-16.so
aymaralima/libboost_date_time.so
aymaralima/liblima-lp-se-number.so
aymaralima/libunistring.so
aymaralima/liblima-lp-eventanalyzer.so
aymaralima/libQt5Quick.so
aymaralima/liblima-lp-lineartextrepresentation.so
aymaralima/liblima-common-xmlconfigurationfiles.so
aymaralima/libQt5Gui.so
aymaralima/liblima-lp-wordsensetagger.so
aymaralima/libgmp.so
aymaralima/libboost_chrono.so
aymaralima/libX11.so
aymaralima/libsystemd.so
aymaralima/libQt5Core.so
aymaralima/libhogweed.so
aymaralima/libffi.so
aymaralima/libnettle.so
aymaralima/libboost_system.so
aymaralima/libfasttext-lima.so
aymaralima/liblz4.so
aymaralima/libQt5QmlModels.so
aymaralima/liblima-lp-tensorflowtokenizer.so
aymaralima/libXext.so
aymaralima/liblima-common-tools.so
aymaralima/liblima-lp-tensorflowspecificentities.so
aymaralima/liblima-common-data.so
aymara-0.4.1.dist-info/top_level.txt
aymara-0.4.1.dist-info/RECORD
aymara-0.4.1.dist-info/LICENCE
aymara-0.4.1.dist-info/METADATA
aymara-0.4.1.dist-info/WHEEL
