Metadata-Version: 2.1
Name: aymara
Version: 0.4.1
Summary: Python bindings to the LIMA linguistic analyzer
Home-page: https://github.com/aymara/lima
Author: Gaël de Chalendar
Author-email: gael.de-chalendar@cea.fr
Project-URL: Bug Tracker, https://github.com/aymara/lima/issues
Project-URL: Wiki, https://github.com/aymara/lima/wiki
Classifier: Programming Language :: Python :: 3
Classifier: License :: OSI Approved :: GNU Affero General Public License v3 or later (AGPLv3+)
Classifier: Operating System :: POSIX :: Linux
Requires-Python: >=3.7
License-File: LICENCE
Requires-Dist: pip (>=22.0)
Requires-Dist: pyconll
Requires-Dist: pydantic
Requires-Dist: requests
Requires-Dist: shiboken2
Requires-Dist: tqdm
Requires-Dist: unix-ar
